[
    {
      "InvoiceNo": "#INV-0010",
      "Doctor": "Ruby Perrin",
      "Amount": "$450",
      "PaidOn": "14 March 2023",
      "Image" : "doctor-thumb-01.jpg",
      "specialist" :"Dental"
      
    },
    {
      "InvoiceNo": "#INV-0009",
      "Doctor": "Dr. Darren Elder",
      "Amount": "$300",
      "PaidOn": "13 March 2023",
      "Image" : "doctor-thumb-02.jpg",
      "specialist" :"Dental"
      
      
    },
    {
      "InvoiceNo": "#INV-0008",
      "Doctor": "Dr. Deborah Angel",
      "Amount": "$150",
      "PaidOn": "12 March 2023",
      "Image" : "doctor-thumb-03.jpg",
      "specialist" :"Cardiology"
      
      
    },
    {
      "InvoiceNo": "#INV-0007",
      "Doctor": "Dr. Sofia Brient",
      "Amount": "$50",
      "PaidOn": "11 March 2023",
      "Image" : "doctor-thumb-04.jpg",
      "specialist" :"Urology"
      
      
    },
    {
      "InvoiceNo": "#INV-0006",
      "Doctor": "Dr. Marvin Campbell",
      "Amount": "$600",
      "PaidOn": "10 March 2023",
      "Image" : "doctor-thumb-05.jpg",
      "specialist" :"Ophthalmology"
      
      
    },
    {
      "InvoiceNo": "#INV-0005",
      "Doctor": "Dr. Katharine Berthold",
      "Amount": "$200",
      "PaidOn": "9 March 2023",
      "Image" : "doctor-thumb-06.jpg",
      "specialist" :"Orthopaedics"
      
      
    },
    {
      "InvoiceNo": "#INV-0004",
      "Doctor": "Dr. Linda Tobin",
      "Amount": "$100",
      "PaidOn": "8 March 2023",
      "Image" : "doctor-thumb-07.jpg",
      "specialist" :"Neurology"
      
      
    },
    {
      "InvoiceNo": "#INV-0003",
      "Doctor": "Dr. Paul Richard",
      "Amount": "$250",
      "PaidOn": "7 March 2023",
      "Image" : "doctor-thumb-08.jpg",
      "specialist" :"Dermatology"
      
      
    },
    {
      "InvoiceNo": "#INV-0002",
      "Doctor": "Dr. John Gibbs",
      "Amount": "$175",
      "PaidOn": "6 March 2023",
      "Image" : "doctor-thumb-09.jpg",
      "specialist" :"Dental"
      
      
    },
    {
      "InvoiceNo": "#INV-0001",
      "Doctor": "Dr. Olga Barlow",
      "Amount": "$550",
      "PaidOn": "5 March 2023",
      "Image" : "doctor-thumb-10.jpg",
      "specialist" :"#0010"
    }
   ]