[
    {
        "id": "1",
        "Image": "patient.jpg",
        "name": "Richard Wilson",
        "patientId": "P0016",
        "location": "Alabama, USA",
        "phone": "+1 952 001 8563",
        "age": "38 Years, Male",
        "bloodGroup": "AB+"
    },
    {
        "id": "2",
        "Image": "patient1.jpg",
        "name": "Charlene Reed",
        "patientId": "P0001",
        "location": "North Carolina, USA",
        "phone": "+1 828 632 9170",
        "age": "29 Years, Female",
        "bloodGroup": "O+"
    },
    {
        "id": "3",
        "Image": "patient2.jpg",
        "name": "Travis Trimble",
        "patientId": "PT0002",
        "location": "Maine, USA",
        "phone": "+1 207 729 9974",
        "age": "23 Years, Male",
        "bloodGroup": "B+"
    },
    {
        "id": "4",
        "Image": "patient3.jpg",
        "name": "Carl Kelly",
        "patientId": "PT0003",
        "location": "Indiana, USA",
        "phone": "+1 260 724 7769",
        "age": "32 Years, Male",
        "bloodGroup": "A+"
    },
    {
        "id": "5",
        "Image": "patient4.jpg",
        "name": "Michelle Fairfax",
        "patientId": "PT0004",
        "location": "Indiana, USA",
        "phone": "+1 504 368 6874",
        "age": "25 Years, Female",
        "bloodGroup": "B+"
    },
    {
        "id": "6",
        "Image": "patient5.jpg",
        "name": "Gina Moore",
        "patientId": "PT0005",
        "location": "Florida, USA",
        "phone": "+1 954 820 7887",
        "age": "25 Years, Female",
        "bloodGroup": "AB-"
    },
    {
        "id": "7",
        "Image": "patient6.jpg",
        "name": "Elsie Gilley",
        "patientId": "PT0006",
        "location": "Kentucky, USA",
        "phone": "+1 315 384 4562",
        "age": "14 Years, Female",
        "bloodGroup": "O-"
    },
    {
        "id": "8",
        "Image": "patient7.jpg",
        "name": "Joan Gardner",
        "patientId": "PT0007",
        "location": "California, USA",
        "phone": "+1 707 2202 603",
        "age": "25 Years, Female",
        "bloodGroup": "A-"
    },
    {
        "id": "9",
        "Image": "patient8.jpg",
        "name": "Daniel Griffing",
        "patientId": "PT0008",
        "location": "New Jersey, USA",
        "phone": "+1 973 773 9497",
        "age": "28 Years, Male",
        "bloodGroup": "O+"
    },
    {
        "id": "10",
        "Image": "patient9.jpg",
        "name": "Walter Roberson",
        "patientId": "PT0009",
        "location": "Florida, USA",
        "phone": "+1 850 358 4445",
        "age": "28 Years, Male",
        "bloodGroup": "A+"
    },
    {
        "id": "11",
        "Image": "patient10.jpg",
        "name": "Robert Rhodes",
        "patientId": "PT0010",
        "location": "California, USA",
        "phone": "+1 858 259 5285",
        "age": "19 Years, Male",
        "bloodGroup": "B+"
    },
    {
        "id": "12",
        "Image": "patient11.jpg",
        "name": "Harry Williams",
        "patientId": "PT0011",
        "location": "Colorado, USA",
        "phone": "+1 303 607 7075",
        "age": "9 Years, Male",
        "bloodGroup": "A-"
    }
]